llmage/__init__.py
llmage-0.0.1.dist-info/METADATA
llmage-0.0.1.dist-info/WHEEL
llmage-0.0.1.dist-info/RECORD
